smssak/__init__.py
smssak/otp.py
smssak-0.2.dist-info/METADATA
smssak-0.2.dist-info/WHEEL
smssak-0.2.dist-info/top_level.txt
smssak-0.2.dist-info/RECORD
