Metadata-Version: 2.1
Name: smssak
Version: 0.2
Summary: A package to send and verify OTPs using smssak service.
Home-page: UNKNOWN
Author: Smassak
Author-email: akreb.corp@gmail.com
License: MIT
Platform: UNKNOWN
Requires-Dist: requests
